setup.py
FNLP/Merge.py
FNLP/__init__.py
FNLP/Language/Character.py
FNLP/Language/Constants.py
FNLP/Language/Keywords.py
FNLP/Language/Paragraphs.py
FNLP/Language/Sentences.py
FNLP/Language/Summarizer.py
FNLP/Language/Tokenizer.py
FNLP/Language/Utils.py
FNLP/Language/Words.py
FNLP/Language/__init__.py
FNLP/LanguageEngines/Enhancers.py
FNLP/LanguageEngines/__init__.py
FNLP/LanguageEngines/Categorizer/Categorizer.py
FNLP/LanguageEngines/Categorizer/CategoryEngine.py
FNLP/LanguageEngines/Categorizer/MainCategories.py
FNLP/LanguageEngines/Categorizer/Models.py
FNLP/LanguageEngines/Categorizer/SubCategories.py
FNLP/LanguageEngines/Categorizer/__init__.py
FNLP/LanguageEngines/Words/Analyzers.py
FNLP/LanguageEngines/Words/Frequency.py
FNLP/LanguageEngines/Words/__init__.py
FNLP/LanguageExtractors/TickerEngine.py
FNLP/LanguageExtractors/__init__.py
FNLP/LanguageManagers/ContentManager.py
FNLP/LanguageManagers/ParagraphsManager.py
FNLP/LanguageManagers/SentencesManager.py
FNLP/LanguageManagers/WordManager.py
FNLP/LanguageManagers/WordsManager.py
FNLP/LanguageManagers/__init__.py
FNLP/LanguageStructure/Sentences.py
FNLP/LanguageStructure/Variables.py
FNLP/LanguageStructure/__init__.py
FNLP/Regex/Constants.py
FNLP/Regex/Re.py
FNLP/Regex/ReDate.py
FNLP/Regex/ReWords.py
FNLP/Regex/__init__.py
FNLP/URL/__init__.py
FairNLP.egg-info/PKG-INFO
FairNLP.egg-info/SOURCES.txt
FairNLP.egg-info/dependency_links.txt
FairNLP.egg-info/requires.txt
FairNLP.egg-info/top_level.txt